deeptrade/__init__.py
deeptrade/constants.py
deeptrade/types.py
deeptrade/diagnostics/__init__.py
deeptrade/diagnostics/eval_model_on_dataset.py
deeptrade/diagnostics/visualize_model_preds.py
deeptrade/env/__init__.py
deeptrade/env/cartpole_continuous.py
deeptrade/env/reward_fns.py
deeptrade/env/single_instrument.py
deeptrade/env/termination_fns.py
deeptrade/env/agents/__init__.py
deeptrade/env/agents/breakout.py
deeptrade/env/agents/ewmac.py
deeptrade/env/agents/hold.py
deeptrade/models/__init__.py
deeptrade/models/basic_ensemble.py
deeptrade/models/gaussian_mlp.py
deeptrade/models/model.py
deeptrade/models/model_env.py
deeptrade/models/model_trainer.py
deeptrade/models/one_dim_tr_model.py
deeptrade/models/util.py
deeptrade/planning/__init__.py
deeptrade/planning/core.py
deeptrade/planning/linear_feedback.py
deeptrade/planning/trajectory_opt.py
deeptrade/util/__init__.py
deeptrade/util/common.py
deeptrade/util/env.py
deeptrade/util/finance.py
deeptrade/util/instrument.py
deeptrade/util/logger.py
deeptrade/util/math.py
deeptrade/util/replay_buffer.py
deeptrade_mbrl-0.1.1.dist-info/METADATA
deeptrade_mbrl-0.1.1.dist-info/WHEEL
deeptrade_mbrl-0.1.1.dist-info/licenses/LICENSE
deeptrade_mbrl-0.1.1.dist-info/RECORD
