Metadata-Version: 2.3
Name: deeptrade-mbrl
Version: 0.1.1
Summary: A simple trading system for backtesting Model Based RL strategies
Author-email: Alexander Quessy <alexander@quessy.io>
License-File: LICENSE
Keywords: backtesting,deep learning,finance,reinforcement learning,trading
Classifier: Development Status :: 3 - Alpha
Classifier: Intended Audience :: Developers
Classifier: License :: OSI Approved :: MIT License
Classifier: Programming Language :: Python :: 3
Classifier: Programming Language :: Python :: 3.10
Classifier: Programming Language :: Python :: 3.11
Requires-Python: >=3.10
Requires-Dist: gymnasium>=0.26.3
Requires-Dist: hydra-core>=1.3.2
Requires-Dist: matplotlib>=3.9.2
Requires-Dist: numpy>=2.1.2
Requires-Dist: omegaconf>=2.3.0
Requires-Dist: pandas>=2.2.3
Requires-Dist: pillow>=10.4.0
Requires-Dist: termcolor>=2.5.0
Requires-Dist: torch>=2.4.1
Requires-Dist: tqdm>=4.66.5
Requires-Dist: wandb>=0.18.3
